<?xml version="1.0" encoding="utf-8"?>
<Product xmlns="http://schemas.microsoft.com/developer/2004/01/bootstrapper" ProductCode="SlimDX.2.0.10.43">
  
  <PackageFiles>
    <PackageFile Name="SlimDX Runtime Net20 (June 2010).msi" />
  </PackageFiles>
  
  <InstallChecks>
    <MsiProductCheck Property="IsInstalled" Product="354D00E0-C7C9-4bc1-BC12-08C4977AA827"/>
  </InstallChecks>
  
  <Commands Reboot="Defer">
    <Command PackageFile="SlimDX Runtime Net20 (June 2010).msi"
             Arguments="/passive"
             EstimatedInstalledBytes="20000000"
             EstimatedInstallSeconds="35"
             EstimatedTempBytes="10000000">
      
      <InstallConditions>
        <!-- Do not attempt to install if the same version is already installed on the system -->
        <BypassIf Property="IsInstalled" Compare="ValueGreaterThan" Value="0"/>

        <!-- Block the install if the user is not an administrator. -->
        <FailIf Property="AdminUser" Compare="ValueNotEqualTo" Value="True" String="AdminRequired" />

        <!-- Block install on Windows 95/98/ME -->
        <FailIf Property="Version9x" Compare="ValueExists" String="IncorrectOS"/>

        <!-- Block install on less than Windows XP SP2 -->
        <FailIf Property="VersionNT" Compare="VersionLessThan" Value="5.1.2" String="IncorrectOS"/>
      </InstallConditions>

      <ExitCodes>
        <ExitCode Value="0" Result="Success" />
        <ExitCode Value="1602" Result="Fail" String="CancelledInstall" />
        <ExitCode Value="1641" Result="SuccessReboot"/>
        <ExitCode Value="3010" Result="SuccessReboot" />
        <DefaultExitCode Result="Fail" FormatMessageFromSystem="true" String="GeneralFailure" />
      </ExitCodes>
    </Command>
  </Commands>
</Product>